transformer_viewer/__init__.py
transformer_viewer/viewer.py
transformer_viewer-0.0.2.dist-info/LICENSE
transformer_viewer-0.0.2.dist-info/METADATA
transformer_viewer-0.0.2.dist-info/WHEEL
transformer_viewer-0.0.2.dist-info/top_level.txt
transformer_viewer-0.0.2.dist-info/RECORD
