Metadata-Version: 2.1
Name: transformer-viewer
Version: 0.0.2
Summary: simple text visualization for transformer
Home-page: https://github.com/Lucas0404/transformer_viewer
Author: lucas_xing
Author-email: xingyun44@hotmail.com
License: UNKNOWN
Platform: UNKNOWN
Classifier: Programming Language :: Python :: 3
Classifier: License :: OSI Approved :: MIT License
Classifier: Operating System :: OS Independent
Requires-Python: >=3.6
